freeplay_python_langgraph/__init__.py
freeplay_python_langgraph/client.py
freeplay_python_langgraph/normalized_message.py
freeplay_python_langgraph/py.typed
freeplay_python_langgraph-0.1.2.dist-info/METADATA
freeplay_python_langgraph-0.1.2.dist-info/WHEEL
freeplay_python_langgraph-0.1.2.dist-info/RECORD
