Metadata-Version: 2.4
Name: freeplay-python-langgraph
Version: 0.1.2
Summary: Freeplay integration for LangGraph and LangChain
Author-email: Nico Tonozzi <nico@freeplay.ai>
Requires-Python: >=3.9
Requires-Dist: freeplay>=0.1.0
Requires-Dist: langchain-community>=0.3.0
Requires-Dist: langchain-core>=0.3.0
Requires-Dist: langgraph>=0.2.0
Requires-Dist: openinference-instrumentation-langchain>=0.1.0
Requires-Dist: opentelemetry-exporter-otlp-proto-http>=1.35.0
Requires-Dist: opentelemetry-sdk>=1.35.0
